{
    "web": {
        "client_id": "527475648594-f4pteb6bget0ntudpg48dtnc5t16nbr5.apps.googleusercontent.com",
        "project_id": "youtube-uplode-265006",
        "auth_uri": "https://accounts.google.com/o/oauth2/auth",
        "token_uri": "https://oauth2.googleapis.com/token",
        "auth_provider_x509_cert_url": "https://www.googleapis.com/oauth2/v1/certs",
        "client_secret": "MNS8ljH40BogTQkaGUEQJSb5",
        "redirect_uris": [
            "https://beta.vicflix.com/auth"
        ],
        "javascript_origins": [
            "https://beta.vicflix.com"
        ]
    }
}